pyde/__init__.py
pyde/__main__.py
pyde/cli.py
pyde/config.py
pyde/data.py
pyde/environment.py
pyde/livereload.py
pyde/pathex.py
pyde/plugins.py
pyde/site.py
pyde/templates.py
pyde/transformer.py
pyde/userlogging.py
pyde/utils.py
pyde/watcher.py
pyde/yaml.py
pyde/js/reload-client.js
pyde/js/vendored/diff-dom/LICENSE.txt
pyde/js/vendored/diff-dom/index.d.ts
pyde/js/vendored/diff-dom/index.js
pyde/js/vendored/diff-dom/index.js.map
pyde/js/vendored/diff-dom/index.min.js
pyde/js/vendored/diff-dom/index.min.js.map
pyde/js/vendored/diff-dom/module.js
pyde/js/vendored/diff-dom/module.js.map
pyde/js/vendored/diff-dom/dts/TraceLogger.d.ts
pyde/js/vendored/diff-dom/dts/index.d.ts
pyde/js/vendored/diff-dom/dts/diffDOM/helpers.d.ts
pyde/js/vendored/diff-dom/dts/diffDOM/index.d.ts
pyde/js/vendored/diff-dom/dts/diffDOM/types.d.ts
pyde/js/vendored/diff-dom/dts/diffDOM/dom/apply.d.ts
pyde/js/vendored/diff-dom/dts/diffDOM/dom/fromVirtual.d.ts
pyde/js/vendored/diff-dom/dts/diffDOM/dom/index.d.ts
pyde/js/vendored/diff-dom/dts/diffDOM/dom/undo.d.ts
pyde/js/vendored/diff-dom/dts/diffDOM/virtual/apply.d.ts
pyde/js/vendored/diff-dom/dts/diffDOM/virtual/diff.d.ts
pyde/js/vendored/diff-dom/dts/diffDOM/virtual/fromDOM.d.ts
pyde/js/vendored/diff-dom/dts/diffDOM/virtual/fromString.d.ts
pyde/js/vendored/diff-dom/dts/diffDOM/virtual/helpers.d.ts
pyde/js/vendored/diff-dom/dts/diffDOM/virtual/index.d.ts
pyde/markdown/__init__.py
pyde/markdown/handler.py
pyde/markdown/extensions/__init__.py
pyde/markdown/extensions/blockquote.py
pyde/markdown/extensions/pm_attr_list.py
pyde/path/__init__.py
pyde/path/filepath.py
pyde/path/local.py
pyde/path/url.py
pyde/path/virtual.py
pyde/templates/default.html
pyde_ssg-0.2.1.dist-info/licenses/LICENSE
pyde_ssg-0.2.1.dist-info/METADATA
pyde_ssg-0.2.1.dist-info/WHEEL
pyde_ssg-0.2.1.dist-info/entry_points.txt
pyde_ssg-0.2.1.dist-info/top_level.txt
pyde_ssg-0.2.1.dist-info/RECORD
