Metadata-Version: 2.4
Name: pyde-ssg
Version: 0.2.1
Requires-Python: >=3.11.0
License-File: LICENSE
Requires-Dist: pyyaml>=6.0
Requires-Dist: markdown>=3.7
Requires-Dist: jinja2>=3.1
Requires-Dist: typing-extensions>4.13
Requires-Dist: watchdog>=6.0
Requires-Dist: websockets>=15.0
Dynamic: license-file
